publications_bootstrap/fields.py
publications_bootstrap/urls.py
publications_bootstrap/apps.py
publications_bootstrap/utils.py
publications_bootstrap/bibtex.py
publications_bootstrap/__init__.py
publications_bootstrap/models/publicationlink.py
publications_bootstrap/models/publication.py
publications_bootstrap/models/type.py
publications_bootstrap/models/__init__.py
publications_bootstrap/models/publicationfile.py
publications_bootstrap/models/catalog.py
publications_bootstrap/static/publications_bootstrap/css/style.css
publications_bootstrap/views/year.py
publications_bootstrap/views/id.py
publications_bootstrap/views/tag.py
publications_bootstrap/views/__init__.py
publications_bootstrap/views/author.py
publications_bootstrap/views/catalog.py
publications_bootstrap/views/unapi.py
publications_bootstrap/templatetags/__init__.py
publications_bootstrap/templatetags/publication_extras.py
publications_bootstrap/migrations/0001_initial.py
publications_bootstrap/migrations/0004_catalog_fk_publication.py
publications_bootstrap/migrations/0002_initial_data.py
publications_bootstrap/migrations/__init__.py
publications_bootstrap/migrations/0003_db_index.py
publications_bootstrap/admin/publicationadmin.py
publications_bootstrap/admin/typeadmin.py
publications_bootstrap/admin/__init__.py
publications_bootstrap/admin/catalogadmin.py
publications_bootstrap/templates/base.html
publications_bootstrap/templates/publications_bootstrap/base.html
publications_bootstrap/templates/publications_bootstrap/pages/tag.html
publications_bootstrap/templates/publications_bootstrap/pages/author.html
publications_bootstrap/templates/publications_bootstrap/pages/years.html
publications_bootstrap/templates/publications_bootstrap/pages/catalog.html
publications_bootstrap/templates/publications_bootstrap/pages/id.html
publications_bootstrap/templates/publications_bootstrap/components/publications_with_thumbnails.html
django_publications_bootstrap-2.3.1.dist-info/metadata.json
django_publications_bootstrap-2.3.1.dist-info/top_level.txt
django_publications_bootstrap-2.3.1.dist-info/DESCRIPTION.rst
django_publications_bootstrap-2.3.1.dist-info/WHEEL
django_publications_bootstrap-2.3.1.dist-info/METADATA
django_publications_bootstrap-2.3.1.dist-info/RECORD
