Metadata-Version: 2.0
Name: django-publications-bootstrap
Version: 2.3.1
Summary: A Django app for managing scientific publications with a Bootstrap-powered UI.
Home-page: https://github.com/mbourqui/django-publications-bootstrap/
Author: Marc Bourqui
Author-email: pypi.kemar@bourqui.org
License: MIT
Download-URL: https://github.com/mbourqui/django-publications-bootstrap/releases/tag/v2.3.1
Keywords: django scientific publications citations references bibliography
Platform: UNKNOWN
Classifier: Development Status :: 5 - Production/Stable
Classifier: Environment :: Web Environment
Classifier: Framework :: Django
Classifier: Framework :: Django :: 1.8
Classifier: Framework :: Django :: 1.9
Classifier: Framework :: Django :: 1.10
Classifier: Framework :: Django :: 1.11
Classifier: Intended Audience :: Developers
Classifier: Intended Audience :: Science/Research
Classifier: License :: OSI Approved :: MIT License
Classifier: Operating System :: OS Independent
Classifier: Programming Language :: Python
Classifier: Programming Language :: Python :: 2
Classifier: Programming Language :: Python :: 2.7
Classifier: Programming Language :: Python :: 3
Classifier: Programming Language :: Python :: 3.4
Classifier: Programming Language :: Python :: 3.5
Classifier: Programming Language :: Python :: 3.6
Classifier: Topic :: Internet :: WWW/HTTP
Classifier: Topic :: Internet :: WWW/HTTP :: Dynamic Content
Requires-Dist: Django (>=1.9.13)
Requires-Dist: Pillow (>=2.4.0)
Requires-Dist: django-countries (>=4.0)
Requires-Dist: django-ordered-model (>=1.4.1)
Requires-Dist: six (>=1.10.0)
Requires-Dist: django-echoices (>=2.2.5)
